gui/__init__.py
pytato/__init__.py
pytato/analysis/__init__.py
pytato/analysis/peptide.py
pytato/analysis/protein.py
pytato/core/__init__.py
pytato/core/machine_learning.py
pytato/core/scales.py
pytato/core/silico.py
pytato/viz/__init__.py
pytato/viz/plots.py
pytatodia-0.6.0.dist-info/licenses/LICENSE
pytatodia-0.6.0.dist-info/METADATA
pytatodia-0.6.0.dist-info/WHEEL
pytatodia-0.6.0.dist-info/top_level.txt
pytatodia-0.6.0.dist-info/RECORD
