Metadata-Version: 2.4
Name: PytatoDIA
Version: 0.6.0
Summary: A Toolbox for Proteomic Analyses and Data Visualization
Home-page: https://github.com/TTCooper-PhD/Pytato
Author: Tyler T. Cooper,Ph.D.
Author-email: tcoope2@gmail.com
Classifier: Programming Language :: Python :: 3
Classifier: License :: OSI Approved :: Apache Software License
Classifier: Operating System :: OS Independent
Requires-Python: >=3.6
License-File: LICENSE
Requires-Dist: matplotlib>=3.3.4
Requires-Dist: seaborn>=0.11.1
Requires-Dist: scipy>=1.5.4
Requires-Dist: biopython>=1.78
Requires-Dist: requests>=2.25.1
Requires-Dist: pandas>=1.2.0
Requires-Dist: numpy>=1.19.0
Requires-Dist: logomaker>=0.8
Requires-Dist: pyteomics>=4.5
Dynamic: author
Dynamic: author-email
Dynamic: classifier
Dynamic: description
Dynamic: description-content-type
Dynamic: home-page
Dynamic: license-file
Dynamic: requires-dist
Dynamic: requires-python
Dynamic: summary
